[
  {
    "tripid": 1,
    "riderid": 1,
    "bicycleid": 2,
    "startstationid": 1,
    "endstationid": 2,
    "starttime": "2026-02-20 08:15:00.000000",
    "endtime": "2026-02-20 08:42:00.000000 +00:00",
    "totaldistance": 4.30,
    "totalelapsedseconds": 1620,
    "totalcost": 0.00
  },
  {
    "tripid": 2,
    "riderid": 4,
    "bicycleid": 1,
    "startstationid": 2,
    "endstationid": 3,
    "starttime": "2026-02-20 09:00:00.000000",
    "endtime": "2026-02-20 09:25:00.000000 +00:00",
    "totaldistance": 6.10,
    "totalelapsedseconds": 1500,
    "totalcost": 3.50
  },
  {
    "tripid": 3,
    "riderid": 7,
    "bicycleid": 7,
    "startstationid": 3,
    "endstationid": 4,
    "starttime": "2026-02-20 12:10:00.000000",
    "endtime": "2026-02-20 12:35:00.000000 +00:00",
    "totaldistance": 3.80,
    "totalelapsedseconds": 1500,
    "totalcost": 3.50
  },
  {
    "tripid": 4,
    "riderid": 10,
    "bicycleid": 2,
    "startstationid": 4,
    "endstationid": 1,
    "starttime": "2026-02-21 07:30:00.000000",
    "endtime": "2026-02-21 07:55:00.000000 +00:00",
    "totaldistance": 5.00,
    "totalelapsedseconds": 1500,
    "totalcost": 0.00
  },
  {
    "tripid": 5,
    "riderid": 1,
    "bicycleid": 1,
    "startstationid": 1,
    "endstationid": 4,
    "starttime": "2026-02-22 17:00:00.000000",
    "endtime": "2026-02-22 17:38:00.000000 +00:00",
    "totaldistance": 7.20,
    "totalelapsedseconds": 2280,
    "totalcost": 0.00
  },
  {
    "tripid": 6,
    "riderid": 2,
    "bicycleid": 4,
    "startstationid": 5,
    "endstationid": 6,
    "starttime": "2026-02-19 08:00:00.000000",
    "endtime": "2026-02-19 08:22:00.000000 +00:00",
    "totaldistance": 3.50,
    "totalelapsedseconds": 1320,
    "totalcost": 0.00
  },
  {
    "tripid": 7,
    "riderid": 6,
    "bicycleid": 7,
    "startstationid": 6,
    "endstationid": 7,
    "starttime": "2026-02-20 13:15:00.000000",
    "endtime": "2026-02-20 13:50:00.000000 +00:00",
    "totaldistance": 5.20,
    "totalelapsedseconds": 2100,
    "totalcost": 0.00
  },
  {
    "tripid": 8,
    "riderid": 2,
    "bicycleid": 4,
    "startstationid": 7,
    "endstationid": 5,
    "starttime": "2026-02-21 18:00:00.000000",
    "endtime": "2026-02-21 18:30:00.000000 +00:00",
    "totaldistance": 4.10,
    "totalelapsedseconds": 1800,
    "totalcost": 0.00
  },
  {
    "tripid": 9,
    "riderid": 3,
    "bicycleid": 3,
    "startstationid": 8,
    "endstationid": 9,
    "starttime": "2026-02-18 10:00:00.000000",
    "endtime": "2026-02-18 10:20:00.000000 +00:00",
    "totaldistance": 2.10,
    "totalelapsedseconds": 1200,
    "totalcost": 0.00
  },
  {
    "tripid": 10,
    "riderid": 9,
    "bicycleid": 5,
    "startstationid": 9,
    "endstationid": 8,
    "starttime": "2026-02-20 16:30:00.000000",
    "endtime": "2026-02-20 16:55:00.000000 +00:00",
    "totaldistance": 2.50,
    "totalelapsedseconds": 1500,
    "totalcost": 0.00
  },
  {
    "tripid": 11,
    "riderid": 3,
    "bicycleid": 10,
    "startstationid": 8,
    "endstationid": 9,
    "starttime": "2026-02-22 08:45:00.000000",
    "endtime": "2026-02-22 09:05:00.000000 +00:00",
    "totaldistance": 2.00,
    "totalelapsedseconds": 1200,
    "totalcost": 0.00
  },
  {
    "tripid": 12,
    "riderid": 5,
    "bicycleid": 8,
    "startstationid": 10,
    "endstationid": 11,
    "starttime": "2026-02-17 07:30:00.000000",
    "endtime": "2026-02-17 07:50:00.000000 +00:00",
    "totaldistance": 2.80,
    "totalelapsedseconds": 1200,
    "totalcost": 0.00
  },
  {
    "tripid": 13,
    "riderid": 8,
    "bicycleid": 9,
    "startstationid": 11,
    "endstationid": 10,
    "starttime": "2026-02-19 15:00:00.000000",
    "endtime": "2026-02-19 15:25:00.000000 +00:00",
    "totaldistance": 3.00,
    "totalelapsedseconds": 1500,
    "totalcost": 0.00
  },
  {
    "tripid": 14,
    "riderid": 5,
    "bicycleid": 8,
    "startstationid": 10,
    "endstationid": 11,
    "starttime": "2026-02-24 08:00:00.000000",
    "endtime": "2026-02-24 08:18:00.000000 +00:00",
    "totaldistance": 2.90,
    "totalelapsedseconds": 1080,
    "totalcost": 0.00
  },
  {
    "tripid": 15,
    "riderid": 7,
    "bicycleid": 11,
    "startstationid": 2,
    "endstationid": 2,
    "starttime": "2026-02-25 07:45:00.000000",
    "endtime": null,
    "totaldistance": null,
    "totalelapsedseconds": null,
    "totalcost": null
  }
]